imagej/__init__.py
imagej/imagej.py
imagej-0.3.1.dist-info/METADATA
imagej-0.3.1.dist-info/RECORD
imagej-0.3.1.dist-info/WHEEL
imagej-0.3.1.dist-info/top_level.txt
