Metadata-Version: 2.1
Name: imagej
Version: 0.3.1
Summary: Python wrapper for ImageJ
Home-page: https://github.com/imagej/imagej.py
Author: Yang Liu, Leon Yang, Curtis Rueden
Author-email: ctrueden@wisc.edu
License: Apache 2.0
Platform: any
